neon_phal_plugin_monitoring/__init__.py
neon_phal_plugin_monitoring-0.0.3.dist-info/LICENSE.md
neon_phal_plugin_monitoring-0.0.3.dist-info/METADATA
neon_phal_plugin_monitoring-0.0.3.dist-info/WHEEL
neon_phal_plugin_monitoring-0.0.3.dist-info/entry_points.txt
neon_phal_plugin_monitoring-0.0.3.dist-info/top_level.txt
neon_phal_plugin_monitoring-0.0.3.dist-info/RECORD
