Metadata-Version: 2.1
Name: neon-phal-plugin-monitoring
Version: 0.0.3
Summary: Core Monitoring Service
Home-page: https://github.com/NeonGeckoCom/neon-phal-plugin-monitoring
Author: Neongecko
Author-email: developers@neon.ai
License: BSD-3
License-File: LICENSE.md
Requires-Dist: neon-utils[network]~=1.1
Requires-Dist: ovos-plugin-manager>=0.0.20,~=0.0
Requires-Dist: ovos-bus-client>=0.0.3,~=0.0
Requires-Dist: ovos-utils>=0.0.30,~=0.0
